simpleshell/__init__.py
simpleshell-0.0.9.dist-info/LICENSE
simpleshell-0.0.9.dist-info/METADATA
simpleshell-0.0.9.dist-info/WHEEL
simpleshell-0.0.9.dist-info/top_level.txt
simpleshell-0.0.9.dist-info/RECORD
