Metadata-Version: 2.1
Name: simpleshell
Version: 0.0.9
Summary: A simple wrapper for synchronous shell commands
Home-page: https://github.com/calvinpark/simpleshell
Author: Calvin Sangbin Park
License: UNKNOWN
Project-URL: Bug Tracker, https://github.com/calvinpark/simpleshell/issues
Platform: UNKNOWN
Classifier: Programming Language :: Python :: 3
Classifier: License :: OSI Approved :: MIT License
Classifier: Operating System :: OS Independent
Requires-Python: >=3
License-File: LICENSE
